imputepy.py
imputepy-1.0.1.dist-info/LICENSE
imputepy-1.0.1.dist-info/METADATA
imputepy-1.0.1.dist-info/WHEEL
imputepy-1.0.1.dist-info/RECORD
